ffxl_p/__init__.py
ffxl_p/example.py
ffxl_p/example_environments.py
ffxl_p/example_rollout.py
ffxl_p/feature-flags.yaml
ffxl_p/py.typed
ffxl_p-0.1.0a2.dist-info/METADATA
ffxl_p-0.1.0a2.dist-info/WHEEL
ffxl_p-0.1.0a2.dist-info/licenses/LICENSE
ffxl_p-0.1.0a2.dist-info/RECORD
