Metadata-Version: 2.4
Name: ffxl-p
Version: 0.1.0a2
Summary: Feature Flags Extra Light - A lightweight, file-based feature flag system with gradual rollout support
Project-URL: Homepage, https://github.com/emilskra/ffxl-p
Project-URL: Documentation, https://github.com/emilskra/ffxl-p#readme
Project-URL: Repository, https://github.com/emilskra/ffxl-p
Project-URL: Issues, https://github.com/emilskra/ffxl-p/issues
Author-email: emilskra <emilagamamedov@gmail.com>
License: MIT
License-File: LICENSE
Keywords: feature-flags,feature-toggles,flags,toggles,yaml
Classifier: Intended Audience :: Developers
Classifier: License :: OSI Approved :: MIT License
Classifier: Programming Language :: Python :: 3
Classifier: Programming Language :: Python :: 3.8
Classifier: Programming Language :: Python :: 3.9
Classifier: Programming Language :: Python :: 3.10
Classifier: Programming Language :: Python :: 3.11
Classifier: Programming Language :: Python :: 3.12
Classifier: Topic :: Software Development :: Libraries :: Python Modules
Classifier: Typing :: Typed
Requires-Python: >=3.8
Requires-Dist: pyyaml>=6.0
